utec_py/__init__.py
utec_py/api.py
utec_py/auth.py
utec_py/const.py
utec_py/exceptions.py
utec_py/devices/__init__.py
utec_py/devices/device.py
utec_py/devices/device_const.py
utec_py/devices/light.py
utec_py/devices/lock.py
utec_py/devices/switch.py
utec_py_lf2b2w-0.3.1.dist-info/METADATA
utec_py_lf2b2w-0.3.1.dist-info/WHEEL
utec_py_lf2b2w-0.3.1.dist-info/top_level.txt
utec_py_lf2b2w-0.3.1.dist-info/RECORD
