Metadata-Version: 2.4
Name: utec_py_LF2b2w
Version: 0.3.1
Summary: A U-Home API client library.
Author-email: Luke Wallis <wallis.luke4@gmail.com>
License: MIT
Project-URL: Homepage, https://github.com/LF2b2w/utec-py
Project-URL: Issues, https://github.com/LF2b2w/utec-py/issues
Keywords: uhome,home automation,api client
Classifier: Programming Language :: Python :: 3.10
Classifier: License :: OSI Approved :: MIT License
Classifier: Operating System :: OS Independent
Requires-Python: >=3.11
Requires-Dist: aiohttp<4.0.0,>=3.7.4
